[
  {
    "City": "Miryalaguda",
    "Total_Shows": 6,
    "Total_Seats": 1808,
    "Booked_Seats": 1116,
    "Collection": "321275.00",
    "Max_Collection": "569535.00",
    "Occupancy": "61.73%"
  },
  {
    "City": "Siddipet",
    "Total_Shows": 2,
    "Total_Seats": 1129,
    "Booked_Seats": 838,
    "Collection": "228925.00",
    "Max_Collection": "302950.00",
    "Occupancy": "74.22%"
  },
  {
    "City": "Jagtial",
    "Total_Shows": 1,
    "Total_Seats": 435,
    "Booked_Seats": 395,
    "Collection": "108625.00",
    "Max_Collection": "119625.00",
    "Occupancy": "90.80%"
  },
  {
    "City": "Sircilla",
    "Total_Shows": 1,
    "Total_Seats": 600,
    "Booked_Seats": 400,
    "Collection": "104390.00",
    "Max_Collection": "146470.00",
    "Occupancy": "66.67%"
  },
  {
    "City": "Kamareddy",
    "Total_Shows": 1,
    "Total_Seats": 486,
    "Booked_Seats": 435,
    "Collection": "119625.00",
    "Max_Collection": "133650.00",
    "Occupancy": "89.51%"
  },
  {
    "City": "Palwancha",
    "Total_Shows": 0,
    "Total_Seats": 0,
    "Booked_Seats": 0,
    "Collection": "0.00",
    "Max_Collection": "0.00",
    "Occupancy": "0.00%"
  },
  {
    "City": "Kothagudem",
    "Total_Shows": 1,
    "Total_Seats": 527,
    "Booked_Seats": 413,
    "Collection": "97935.00",
    "Max_Collection": "126395.00",
    "Occupancy": "78.37%"
  },
  {
    "City": "Bodhan",
    "Total_Shows": 0,
    "Total_Seats": 0,
    "Booked_Seats": 0,
    "Collection": "0.00",
    "Max_Collection": "0.00",
    "Occupancy": "0.00%"
  },
  {
    "City": "Sangareddy",
    "Total_Shows": 2,
    "Total_Seats": 1153,
    "Booked_Seats": 1036,
    "Collection": "270360.00",
    "Max_Collection": "296735.00",
    "Occupancy": "89.85%"
  },
  {
    "City": "Metpally",
    "Total_Shows": 1,
    "Total_Seats": 656,
    "Booked_Seats": 460,
    "Collection": "110840.00",
    "Max_Collection": "140260.00",
    "Occupancy": "70.12%"
  }
]