[
  {
    "City": "Miryalaguda",
    "Total_Shows": 21,
    "Total_Seats": 6938,
    "Booked_Seats": 2613,
    "Collection": "693390.00",
    "Max_Collection": "2131140.00",
    "Occupancy": "37.66%"
  },
  {
    "City": "Siddipet",
    "Total_Shows": 8,
    "Total_Seats": 4516,
    "Booked_Seats": 2396,
    "Collection": "652225.00",
    "Max_Collection": "1211800.00",
    "Occupancy": "53.06%"
  },
  {
    "City": "Jagtial",
    "Total_Shows": 4,
    "Total_Seats": 1740,
    "Booked_Seats": 1390,
    "Collection": "382250.00",
    "Max_Collection": "478500.00",
    "Occupancy": "79.89%"
  },
  {
    "City": "Sircilla",
    "Total_Shows": 4,
    "Total_Seats": 2400,
    "Booked_Seats": 1096,
    "Collection": "279300.00",
    "Max_Collection": "585880.00",
    "Occupancy": "45.67%"
  },
  {
    "City": "Kamareddy",
    "Total_Shows": 4,
    "Total_Seats": 1944,
    "Booked_Seats": 1199,
    "Collection": "329725.00",
    "Max_Collection": "534600.00",
    "Occupancy": "61.68%"
  },
  {
    "City": "Palwancha",
    "Total_Shows": 0,
    "Total_Seats": 0,
    "Booked_Seats": 0,
    "Collection": "0.00",
    "Max_Collection": "0.00",
    "Occupancy": "0.00%"
  },
  {
    "City": "Kothagudem",
    "Total_Shows": 4,
    "Total_Seats": 2108,
    "Booked_Seats": 1236,
    "Collection": "284140.00",
    "Max_Collection": "505580.00",
    "Occupancy": "58.63%"
  },
  {
    "City": "Bodhan",
    "Total_Shows": 0,
    "Total_Seats": 0,
    "Booked_Seats": 0,
    "Collection": "0.00",
    "Max_Collection": "0.00",
    "Occupancy": "0.00%"
  },
  {
    "City": "Sangareddy",
    "Total_Shows": 8,
    "Total_Seats": 4520,
    "Booked_Seats": 3728,
    "Collection": "975635.00",
    "Max_Collection": "1156120.00",
    "Occupancy": "82.48%"
  },
  {
    "City": "Metpally",
    "Total_Shows": 4,
    "Total_Seats": 2624,
    "Booked_Seats": 1724,
    "Collection": "398770.00",
    "Max_Collection": "561040.00",
    "Occupancy": "65.70%"
  }
]