[
  {
    "City": "Miryalaguda",
    "Total_Shows": 5,
    "Total_Seats": 1209,
    "Booked_Seats": 1180,
    "Collection": "906200.00",
    "Max_Collection": "920700.00",
    "Occupancy": "97.60%"
  },
  {
    "City": "Siddipet",
    "Total_Shows": 1,
    "Total_Seats": 553,
    "Booked_Seats": 293,
    "Collection": "219800.00",
    "Max_Collection": "420200.00",
    "Occupancy": "52.98%"
  },
  {
    "City": "Jagtial",
    "Total_Shows": 5,
    "Total_Seats": 2175,
    "Booked_Seats": 1795,
    "Collection": "493625.00",
    "Max_Collection": "598125.00",
    "Occupancy": "82.53%"
  },
  {
    "City": "Sircilla",
    "Total_Shows": 4,
    "Total_Seats": 2400,
    "Booked_Seats": 893,
    "Collection": "231295.00",
    "Max_Collection": "585880.00",
    "Occupancy": "37.21%"
  },
  {
    "City": "Kamareddy",
    "Total_Shows": 5,
    "Total_Seats": 2430,
    "Booked_Seats": 1365,
    "Collection": "375375.00",
    "Max_Collection": "668250.00",
    "Occupancy": "56.17%"
  },
  {
    "City": "Palwancha",
    "Total_Shows": 0,
    "Total_Seats": 0,
    "Booked_Seats": 0,
    "Collection": "0.00",
    "Max_Collection": "0.00",
    "Occupancy": "0.00%"
  },
  {
    "City": "Kothagudem",
    "Total_Shows": 5,
    "Total_Seats": 2587,
    "Booked_Seats": 1545,
    "Collection": "358065.00",
    "Max_Collection": "618775.00",
    "Occupancy": "59.72%"
  },
  {
    "City": "Bodhan",
    "Total_Shows": 0,
    "Total_Seats": 0,
    "Booked_Seats": 0,
    "Collection": "0.00",
    "Max_Collection": "0.00",
    "Occupancy": "0.00%"
  },
  {
    "City": "Sangareddy",
    "Total_Shows": 1,
    "Total_Seats": 658,
    "Booked_Seats": 610,
    "Collection": "476600.00",
    "Max_Collection": "507200.00",
    "Occupancy": "92.71%"
  },
  {
    "City": "Metpally",
    "Total_Shows": 5,
    "Total_Seats": 3280,
    "Booked_Seats": 1879,
    "Collection": "451675.00",
    "Max_Collection": "701300.00",
    "Occupancy": "57.29%"
  }
]