[
  {
    "City": "Miryalaguda",
    "Total_Shows": 5,
    "Total_Seats": 1330,
    "Booked_Seats": 260,
    "Collection": "101855.00",
    "Max_Collection": "477740.00",
    "Occupancy": "19.55%"
  },
  {
    "City": "Siddipet",
    "Total_Shows": 2,
    "Total_Seats": 1129,
    "Booked_Seats": 176,
    "Collection": "48350.00",
    "Max_Collection": "302950.00",
    "Occupancy": "15.59%"
  },
  {
    "City": "Jagtial",
    "Total_Shows": 1,
    "Total_Seats": 435,
    "Booked_Seats": 101,
    "Collection": "27775.00",
    "Max_Collection": "119625.00",
    "Occupancy": "23.22%"
  },
  {
    "City": "Sircilla",
    "Total_Shows": 0,
    "Total_Seats": 0,
    "Booked_Seats": 0,
    "Collection": "0.00",
    "Max_Collection": "0.00",
    "Occupancy": "0.00%"
  },
  {
    "City": "Kamareddy",
    "Total_Shows": 1,
    "Total_Seats": 486,
    "Booked_Seats": 86,
    "Collection": "23650.00",
    "Max_Collection": "133650.00",
    "Occupancy": "17.70%"
  },
  {
    "City": "Palwancha",
    "Total_Shows": 0,
    "Total_Seats": 0,
    "Booked_Seats": 0,
    "Collection": "0.00",
    "Max_Collection": "0.00",
    "Occupancy": "0.00%"
  },
  {
    "City": "Kothagudem",
    "Total_Shows": 0,
    "Total_Seats": 0,
    "Booked_Seats": 0,
    "Collection": "0.00",
    "Max_Collection": "0.00",
    "Occupancy": "0.00%"
  },
  {
    "City": "Bodhan",
    "Total_Shows": 0,
    "Total_Seats": 0,
    "Booked_Seats": 0,
    "Collection": "0.00",
    "Max_Collection": "0.00",
    "Occupancy": "0.00%"
  },
  {
    "City": "Sangareddy",
    "Total_Shows": 2,
    "Total_Seats": 1153,
    "Booked_Seats": 476,
    "Collection": "129645.00",
    "Max_Collection": "296735.00",
    "Occupancy": "41.28%"
  },
  {
    "City": "Metpally",
    "Total_Shows": 1,
    "Total_Seats": 656,
    "Booked_Seats": 38,
    "Collection": "9300.00",
    "Max_Collection": "140260.00",
    "Occupancy": "5.79%"
  }
]